kinfer/requirements.txt
kinfer/__init__.py
kinfer/py.typed
kinfer/rust_bindings.pyi
kinfer/rust_bindings.cpython-314-darwin.so
kinfer/rust/Cargo.toml
kinfer/rust/src/logger.rs
kinfer/rust/src/types.rs
kinfer/rust/src/lib.rs
kinfer/rust/src/model.rs
kinfer/scripts/plot_ndjson.py
kinfer/export/serialize.py
kinfer/export/__init__.py
kinfer/export/jax.py
kinfer/export/pytorch.py
kinfer/rust_bindings/Cargo.toml
kinfer/rust_bindings/pyproject.toml
kinfer/rust_bindings/rust_bindings.pyi
kinfer/rust_bindings/src/lib.rs
kinfer/rust_bindings/src/bin/stub_gen.rs
kinfer-0.6.1.dist-info/RECORD
kinfer-0.6.1.dist-info/WHEEL
kinfer-0.6.1.dist-info/top_level.txt
kinfer-0.6.1.dist-info/METADATA
kinfer-0.6.1.dist-info/licenses/LICENSE
