Metadata-Version: 2.4
Name: kinfer
Version: 0.6.1
Summary: Tool to make it easier to run a model on a real robot
Home-page: https://github.com/kscalelabs/kinfer.git
Author: K-Scale Labs
Requires-Python: >=3.11
License-File: LICENSE
Requires-Dist: onnx
Requires-Dist: onnxruntime==1.20.0
Provides-Extra: dev
Requires-Dist: black; extra == "dev"
Requires-Dist: darglint; extra == "dev"
Requires-Dist: mypy; extra == "dev"
Requires-Dist: pytest; extra == "dev"
Requires-Dist: ruff; extra == "dev"
Requires-Dist: types-tensorflow; extra == "dev"
Provides-Extra: pytorch
Requires-Dist: torch; extra == "pytorch"
Provides-Extra: jax
Requires-Dist: tensorflow; extra == "jax"
Requires-Dist: tf2onnx>=1.16.0; extra == "jax"
Requires-Dist: jax; extra == "jax"
Requires-Dist: equinox; extra == "jax"
Requires-Dist: numpy<2; extra == "jax"
Provides-Extra: vis
Requires-Dist: matplotlib; extra == "vis"
Requires-Dist: numpy; extra == "vis"
Provides-Extra: all
Requires-Dist: black; extra == "all"
Requires-Dist: darglint; extra == "all"
Requires-Dist: mypy; extra == "all"
Requires-Dist: pytest; extra == "all"
Requires-Dist: ruff; extra == "all"
Requires-Dist: types-tensorflow; extra == "all"
Requires-Dist: torch; extra == "all"
Requires-Dist: tensorflow; extra == "all"
Requires-Dist: tf2onnx>=1.16.0; extra == "all"
Requires-Dist: jax; extra == "all"
Requires-Dist: equinox; extra == "all"
Requires-Dist: numpy<2; extra == "all"
Requires-Dist: matplotlib; extra == "all"
Requires-Dist: numpy; extra == "all"
Dynamic: author
Dynamic: description
Dynamic: description-content-type
Dynamic: home-page
Dynamic: license-file
Dynamic: provides-extra
Dynamic: requires-dist
Dynamic: requires-python
Dynamic: summary
